Metadata-Version: 2.1
Name: prtty
Version: 0.0.4
Summary: prtty
Home-page: https://github.com/remorses/prtty
Author: Tommaso De Rossi
Author-email: daer.tommy@gmail.com
License: Apache Software License 2.0
Keywords: TODO
Platform: UNKNOWN
Classifier: Intended Audience :: Information Technology
Classifier: Programming Language :: Python :: 3
Classifier: Programming Language :: Python :: 3.6
Classifier: Programming Language :: Python :: 3.7
